pop_except/conf.py
pop_except/init.py
pop_except/version.py
pop_except/except/init.py
pop_except/except/hook/default.py
pop_except/except/hook/notrace.py
pop_except/except/hook/contracts/init.py
pop_except-0.1.0.dist-info/LICENSE
pop_except-0.1.0.dist-info/METADATA
pop_except-0.1.0.dist-info/WHEEL
pop_except-0.1.0.dist-info/entry_points.txt
pop_except-0.1.0.dist-info/top_level.txt
pop_except-0.1.0.dist-info/RECORD
