Metadata-Version: 2.1
Name: pop-except
Version: 0.1.0
Summary: Contracts, subs, and environment for handling exceptions in POP
Home-page: https://gitlab.com/vmware/pop/pop-except
Author: Tyler Johnson
Author-email: tyjohnson@vmware.com
License: UNKNOWN
Platform: UNKNOWN
Classifier: Environment :: Console
Classifier: Intended Audience :: Developers
Classifier: Intended Audience :: Information Technology
Classifier: Intended Audience :: System Administrators
Classifier: Operating System :: OS Independent
Classifier: Programming Language :: Python
Classifier: Programming Language :: Python :: 3.7
Classifier: Programming Language :: Python :: 3.8
Classifier: Programming Language :: Python :: 3.9
Classifier: Programming Language :: Python :: 3.10
Classifier: Development Status :: 5 - Production/Stable
Requires-Python: >=3.7
License-File: LICENSE
Requires-Dist: pop (>=17.0)
